{
  "meta": {
    "type": "Wikidata::SnowflakeQueryPattern",
    "entity_id": 26415062,
    "bindings": [
      [
        156,
        20748734
      ],
      [
        155,
        20965691
      ],
      [
        50,
        65666
      ]
    ]
  },
  "pattern": {
    "projected": [
      "?x",
      "?y1"
    ],
    "subpatterns": [
      {
        "meta": {
          "type": "Wikidata::StarQueryGenerator"
        },
        "pattern": {
          "center": "?x",
          "edges": [
            {
              "predicate": 156,
              "object": 20748734
            },
            {
              "predicate": 155,
              "object": "?y1"
            },
            {
              "predicate": 50,
              "object": "?y2"
            }
          ]
        }
      }
    ]
  }
}
